collect_db_models/__init__.py
collect_db_models-0.0.6.dist-info/METADATA
collect_db_models-0.0.6.dist-info/WHEEL
collect_db_models-0.0.6.dist-info/entry_points.txt
collect_db_models-0.0.6.dist-info/RECORD
