Metadata-Version: 2.3
Name: collect-db-models
Version: 0.0.6
Summary: collect sqlalchemy models to one file(eg. __init__.py)
Author: codeif
Author-email: me@codeif.com
Requires-Python: >=3.10
Classifier: Programming Language :: Python :: 3
Classifier: Programming Language :: Python :: 3.10
Classifier: Programming Language :: Python :: 3.11
Classifier: Programming Language :: Python :: 3.12
Classifier: Programming Language :: Python :: 3.13
Requires-Dist: flask (>=1.0.0)
